{
  "chain_name": "jackal-mainnet",
  "registry_name": "jackal-mainnet",
  "api": [
    { "provider": "Ryddd", "address": "https://api-jackal.provewithryd.xyz" }
  ],
  "rpc": [
    { "provider": "Ryddd", "address": "https://rpc-jackal.provewithryd.xyz" }
  ],
  "grpc": [
    { "provider": "Ryddd", "address": "https://grpc-jackal.provewithryd.xyz" }
  ],
  "sdk_version": "0.50.7",
  "coin_type": "118",
  "min_tx_fee": "500",
  "addr_prefix": "jkl",
  "logo": "/logos/jackal.svg",
  "assets": [
    {
      "base": "ujkl",
      "name": "Jackal",
      "symbol": "JKL",
      "exponent": "6",
      "coingecko_id": "jackal-protocol",
      "logo": "/logos/jackal.svg"
    }
  ],
  "fees": {
    "fee_tokens": [
      {
        "denom": "ujkl",
        "fixed_min_gas_price": 100000,
        "low_gas_price": 0.01,
        "average_gas_price": 0.05,
        "high_gas_price": 0.1
      }
    ]
  }
}
